media/__init__.py
media/funciones.py
media_calc-0.2.5.dist-info/METADATA
media_calc-0.2.5.dist-info/WHEEL
media_calc-0.2.5.dist-info/top_level.txt
media_calc-0.2.5.dist-info/RECORD
